avd_compose/__init__.py
avd_compose/androidstudio/__init__.py
avd_compose/androidstudio/avdmanager.py
avd_compose/androidstudio/emulator.py
avd_compose/androidstudio/sdkmanager.py
avd_compose/cli.py
avd_compose/configs/v1/__init__.py
avd_compose/parser.py
avd_compose/utils/formatter.py
avd_compose/utils/shell.py
avd_compose/utils/yaml.py
avd_compose-0.5.5.dist-info/entry_points.txt
avd_compose-0.5.5.dist-info/LICENSE
avd_compose-0.5.5.dist-info/WHEEL
avd_compose-0.5.5.dist-info/METADATA
avd_compose-0.5.5.dist-info/RECORD
